x84/__init__.py
x84/client.py
x84/cmdline.py
x84/db.py
x84/engine.py
x84/fail2ban.py
x84/msgpoll.py
x84/rlogin.py
x84/server.py
x84/sftp.py
x84/ssh.py
x84/telnet.py
x84/terminal.py
x84/webserve.py
x84/bbs/__init__.py
x84/bbs/ansiwin.py
x84/bbs/dbproxy.py
x84/bbs/door.py
x84/bbs/editor.py
x84/bbs/exception.py
x84/bbs/ini.py
x84/bbs/ipc.py
x84/bbs/lightbar.py
x84/bbs/modem.py
x84/bbs/msgbase.py
x84/bbs/output.py
x84/bbs/pager.py
x84/bbs/script_def.py
x84/bbs/selector.py
x84/bbs/session.py
x84/bbs/telnet.py
x84/bbs/userbase.py
x84/default/__init__.py
x84/default/charset.py
x84/default/chat.py
x84/default/common.py
x84/default/editor.py
x84/default/editor.txt
x84/default/fbrowse.py
x84/default/hackernews.py
x84/default/ircchat.py
x84/default/lc.py
x84/default/logoff.py
x84/default/main.py
x84/default/matrix.py
x84/default/matrix_sftp.py
x84/default/matrix_ssh.py
x84/default/msgarea.py
x84/default/news.py
x84/default/nua.py
x84/default/ol.py
x84/default/online.py
x84/default/profile.py
x84/default/pwreset.py
x84/default/sesame.py
x84/default/si.py
x84/default/sysop.py
x84/default/telnet.py
x84/default/test_keyboard_keys.py
x84/default/tetris.py
x84/default/top.py
x84/default/userlist.py
x84/default/vote.py
x84/default/weather.py
x84/default/art/1984.asc
x84/default/art/__init__.py
x84/default/art/bbslist.asc
x84/default/art/bulletins.ans
x84/default/art/bulletinsmenu.ans
x84/default/art/callers.ans
x84/default/art/callers2.ans
x84/default/art/callers3.ans
x84/default/art/callers4.ans
x84/default/art/callers5.ans
x84/default/art/chat.ans
x84/default/art/encoding.ans
x84/default/art/ga-main.ans
x84/default/art/hx-msg.ans
x84/default/art/irc.asc
x84/default/art/jah-menu.ans
x84/default/art/lc.asc
x84/default/art/logoff.ans
x84/default/art/main1.asc
x84/default/art/main2.asc
x84/default/art/matrix.ans
x84/default/art/msgs.asc
x84/default/art/news.ans
x84/default/art/news.txt
x84-2.0.15.dist-info/DESCRIPTION.rst
x84-2.0.15.dist-info/METADATA
x84-2.0.15.dist-info/RECORD
x84-2.0.15.dist-info/WHEEL
x84-2.0.15.dist-info/entry_points.txt
x84-2.0.15.dist-info/metadata.json
x84-2.0.15.dist-info/top_level.txt
