Metadata-Version: 2.0
Name: x84
Version: 2.0.15
Summary: Framework for Telnet and SSH BBS or MUD server development with example default bbs board
Home-page: http://x84.rtfd.org
Author: Jeff Quast
Author-email: contact@jeffquast.com
License: ISC
Keywords: telnet ssh terminal server ansi bbs mud curses utf8 cp437
Platform: UNKNOWN
Classifier: Environment :: Console :: Curses
Classifier: Environment :: Console
Classifier: Intended Audience :: Developers
Classifier: License :: OSI Approved :: ISC License (ISCL)
Classifier: Natural Language :: English
Classifier: Operating System :: MacOS :: MacOS X
Classifier: Operating System :: POSIX :: BSD :: FreeBSD
Classifier: Operating System :: POSIX :: BSD :: NetBSD
Classifier: Operating System :: POSIX :: BSD :: OpenBSD
Classifier: Operating System :: POSIX :: BSD
Classifier: Operating System :: POSIX :: Linux
Classifier: Operating System :: POSIX :: SunOS/Solaris
Classifier: Operating System :: POSIX
Classifier: Operating System :: Unix
Classifier: Programming Language :: Python :: 2 :: Only
Classifier: Programming Language :: Python :: 2.6
Classifier: Programming Language :: Python :: 2.7
Classifier: Topic :: Artistic Software
Classifier: Topic :: Communications :: BBS
Classifier: Topic :: Software Development :: User Interfaces
Classifier: Topic :: Terminals :: Telnet
Classifier: Topic :: Terminals
Requires-Dist: blessed (>=1.9.5,<2.0.0)
Requires-Dist: feedparser (==5.1.3)
Requires-Dist: html2text (==2014.12.29)
Requires-Dist: irc (==11.0.1)
Requires-Dist: jaraco.timing (==1.1)
Requires-Dist: jaraco.util (==10.6)
Requires-Dist: more-itertools (==2.2)
Requires-Dist: python-dateutil (==2.3)
Requires-Dist: requests (==2.5.1)
Requires-Dist: sauce (==1.1)
Requires-Dist: six (==1.9.0)
Requires-Dist: sqlitedict (==1.1.0)
Requires-Dist: wsgiref (==0.1.2)
Requires-Dist: xmodem (==0.3.2)
Provides-Extra: with_crypto
Requires-Dist: bcrypt (==1.1.0); extra == 'with_crypto'
Requires-Dist: cffi (==1.7.0); extra == 'with_crypto'
Requires-Dist: cherrypy (==3.6.0); extra == 'with_crypto'
Requires-Dist: cryptography (==1.2.3); extra == 'with_crypto'
Requires-Dist: ecdsa (==0.11); extra == 'with_crypto'
Requires-Dist: enum34 (==1.0.4); extra == 'with_crypto'
Requires-Dist: paramiko (==1.15.2); extra == 'with_crypto'
Requires-Dist: pyOpenSSL (==0.14); extra == 'with_crypto'
Requires-Dist: pyasn1 (==0.1.7); extra == 'with_crypto'
Requires-Dist: pycparser (==2.10); extra == 'with_crypto'
Requires-Dist: pycrypto (==2.6.1); extra == 'with_crypto'
Requires-Dist: web.py (==0.37); extra == 'with_crypto'
